rtcpxr_collector/__init__.py
rtcpxr_collector/sip.py
rtcpxr_collector/sipparser.py
rtcpxr_collector/vqcollector.py
rtcpxr_collector-0.1.7.dist-info/LICENSE
rtcpxr_collector-0.1.7.dist-info/METADATA
rtcpxr_collector-0.1.7.dist-info/WHEEL
rtcpxr_collector-0.1.7.dist-info/top_level.txt
rtcpxr_collector-0.1.7.dist-info/RECORD
