Metadata-Version: 2.1
Name: rtcpxr-collector
Version: 0.1.7
Summary: A python library for Collecting RTCP-XR (RFC 3611) SIP quality packets
Home-page: https://github.com/paradxum/rtcpxr_collector
Author: Eric Schultz
Author-email: eric.schultz@cyvon.com
License: UNKNOWN
Platform: UNKNOWN
Classifier: Programming Language :: Python :: 3
Classifier: License :: OSI Approved :: GNU General Public License v3 (GPLv3)
Classifier: Operating System :: OS Independent
Requires-Python: >=3.1
